islex/__init__.py
islex/load.py
islex/tokens.py
islex/data/__init__.py
islex-0.2.4.dist-info/DESCRIPTION.rst
islex-0.2.4.dist-info/METADATA
islex-0.2.4.dist-info/RECORD
islex-0.2.4.dist-info/WHEEL
islex-0.2.4.dist-info/entry_points.txt
islex-0.2.4.dist-info/metadata.json
islex-0.2.4.dist-info/top_level.txt
islex-0.2.4.dist-info/zip-safe
