Metadata-Version: 2.0
Name: islex
Version: 0.2.4
Summary: Utility classes to support easy loading and manipulation of dictionary-to-pronunciation.
Home-page: https://github.com/jkahn/islex
Author: Jeremy G. Kahn
Author-email: jeremy@trochee.net
License: MIT license
Keywords: islex
Platform: UNKNOWN
Classifier: Development Status :: 2 - Pre-Alpha
Classifier: Intended Audience :: Developers
Classifier: License :: OSI Approved :: MIT License
Classifier: Natural Language :: English
Classifier: Programming Language :: Python :: 2
Classifier: Programming Language :: Python :: 2.6
Classifier: Programming Language :: Python :: 2.7
Classifier: Programming Language :: Python :: 3
Classifier: Programming Language :: Python :: 3.3
Classifier: Programming Language :: Python :: 3.4
Classifier: Programming Language :: Python :: 3.5
Requires-Dist: attrs
Requires-Dist: enum34
Requires-Dist: six
